<?xml version="1.0" encoding="UTF-8"?>
<odoo>
    <data>
        <report
            id="report_receipt_menu_penerimaan"
            string="Penerimaan"
            model="account.move"
            report_type="qweb-pdf"
            file="account.invoice"
            name="document_tanda_terima.penerimaan_kas_report"
        />

        <template id="penerimaan_kas_report_document">
            <t t-call="web.external_layout">
                <t t-set="o" t-value="o.with_context(lang=lang)" />
                <div class="page">
                    <div id="header1">
                        <h3 style="width: 100%; text-align: center;">
                            <u>Bukti Penerimaan <span t-field="o.journal_id.type"/></u>
                        </h3>
                    </div>
                    <p/>
                    <table style="width: 100%; text-align: left;">
                    <tr><td style="width: 20%; text-align: left;">Document No.</td><td style="width: 3%; text-align: left;">:</td><td style="width: 77%; text-align: left;"><span t-field="o.name"/></td></tr>
                    <tr><td style="width: 20%; text-align: left;">Diterima dari</td><td style="width: 3%; text-align: left;">:</td><td style="width: 77%; text-align: left;"><span t-field="o.partner_id.name"/></td></tr>
                    <tr><td style="width: 20%; text-align: left;">Sejumlah</td><td style="width: 3%; text-align: left;">:</td><td style="width: 77%; text-align: left;"><span t-field="o.amount"/></td></tr>
                    <tr><td style="width: 20%; text-align: left;">Terbilang</td><td style="width: 3%; text-align: left;">:</td><td style="width: 77%; text-align: left;"><span t-field="o.amount_to_text"/></td></tr>
                    <tr><td style="width: 20%; text-align: left;">Paoting Date</td><td style="width: 3%; text-align: left;">:</td><td style="width: 77%; text-align: left;"><span t-field="o.date"/></td></tr>
                    <tr><td style="width: 20%; text-align: left;">Referensi</td><td style="width: 3%; text-align: left;">:</td><td style="width: 77%; text-align: left;"><span t-field="o.ref"/></td></tr>
                    </table>
                    <p/>
                    <table class="table table-sm o_main_table" name="line_table">
                        <thead>
                            <tr>
                                <th class="text-left"><span>No.</span></th>
                                <t t-set="colspan" t-value="3"/>
                                <th class="text-left"><span>Nama COA</span></th>
                                <t t-set="colspan" t-value="5"/>
                                <th class="text-left"><span>Untuk Keperluan / Keterangan</span></th>
                                <th class="text-right">
                                    <span groups="account.group_show_line_subtotals_tax_excluded">Jumlah</span>
                                </th>
                            </tr>
                        </thead>
                        <tbody class="invoice_tbody">
                            <t t-set="remaining_loop" t-value="8"/>
                            <t t-set="i" t-value="1"/>
                            <t t-foreach="o.line_ids" t-as="line">
                                <t t-if="line.credit != 0">
                                    <tr>
                                        <td><t t-esc="i"/></td>
                                        <td><span t-field="line.account_id.name"/></td>
                                        <td><span t-field="line.name"/></td>
                                        <td class="text-right"><span t-field="line.credit" class="text-right"/></td>
                                    </tr>
                                    <t t-set="remaining_loop" t-value="remaining_loop-1"/>
                                    <t t-set="i" t-value="i+1"/>
                                </t>
                            </t>
                            <t t-if="remaining_loop > 0">
                                <t t-foreach="range(1,remaining_loop)" t-as="loop">
                                    <tr>
                                        <td>&#160;</td>
                                        <td>&#160;</td>
                                        <td>&#160;</td>
                                        <td>&#160;</td>
                                    </tr>
                                </t>
                            </t>
                        </tbody>
                    </table>
                    <hr/>
                    <table style="width: 100%;">
                        <tr>
                            <td style="width: 35%; text-align: left;">Disetujui</td>
                            <td style="width: 35%; text-align: left;">Diperiksa dan di bayar</td>
                            <td style="width: 30%; text-align: left;">Jumlah Uang telah di terima</td>
                        </tr>
                        <tr>
                            <td style="width: 35%; text-align: left;">Tgl._____________</td>
                            <td style="width: 35%; text-align: left;">Tgl._____________</td>
                            <td style="width: 30%; text-align: left;">Tanda tangan</td>
                        </tr>
                        <tr>
                            <td style="width: 35%; text-align: left;">&#160;</td>
                            <td style="width: 35%; text-align: left;">&#160;</td>
                            <td style="width: 30%; text-align: left;">&#160;</td>
                        </tr>
                        <tr>
                            <td style="width: 35%; text-align: left;">&#160;</td>
                            <td style="width: 35%; text-align: left;">&#160;</td>
                            <td style="width: 30%; text-align: left;">&#160;</td>
                        </tr>
                        <tr>
                            <td style="width: 35%; text-align: left;">&#160;</td>
                            <td style="width: 35%; text-align: left;">&#160;</td>
                            <td style="width: 30%; text-align: left;">&#160;</td>
                        </tr>
                        <tr>
                            <td style="width: 35%; text-align: left;">( Pimpinan )</td>
                            <td style="width: 35%; text-align: left;">( Kasir)</td>
                            <td style="width: 30%; text-align: left;">( _______________ )</td>
                        </tr>
                    </table>
                </div>
            </t>
        </template>

        <template id="penerimaan_kas_report">
            <t t-call="web.html_container">
                <t t-foreach="docs" t-as="o">
                    <t t-set="lang" t-value="o.create_uid.sudo().lang"/>
                    <t t-call="document_tanda_terima.penerimaan_kas_report_document" t-lang="lang"/>
                </t>
            </t>
        </template>
        

    </data>
</odoo>